flag_gen/__init__.py
flag_gen/__main__.py
flag_gen-0.0.2.dist-info/LICENSE
flag_gen-0.0.2.dist-info/METADATA
flag_gen-0.0.2.dist-info/WHEEL
flag_gen-0.0.2.dist-info/entry_points.txt
flag_gen-0.0.2.dist-info/top_level.txt
flag_gen-0.0.2.dist-info/RECORD
