Metadata-Version: 2.1
Name: flag-gen
Version: 0.0.2
Summary: A CTF leet flag generator
Home-page: https://github.com/Konano/ctf-flag-generator
Author: Konano
Author-email: w@nano.ac
License: MIT
Keywords: ctf,flag,generator
Platform: UNKNOWN
Classifier: Development Status :: 3 - Alpha
Classifier: Intended Audience :: Developers
Classifier: Topic :: Security
Classifier: Topic :: Security :: Cryptography
Classifier: License :: OSI Approved :: MIT License
Classifier: Programming Language :: Python :: 3
Classifier: Programming Language :: Python :: 3.3
Classifier: Programming Language :: Python :: 3.4
Classifier: Programming Language :: Python :: 3.5
Classifier: Programming Language :: Python :: 3.6
Classifier: Programming Language :: Python :: 3.7
Classifier: Programming Language :: Python :: Implementation :: CPython
License-File: LICENSE
